Twista-0.3.3.data/scripts/twista
twista/__init__.py
twista/dm.py
twista/jupyter.py
twista/navigator.py
twista/neo4j.py
twista/recorder.py
twista/static/style.css
twista/static/twitter-logo.png
twista/static/utils.js
twista/templates/base.html
twista/templates/card_snippet.html
twista/templates/index.html
twista/templates/search.html
twista/templates/tag.html
twista/templates/tweet.html
twista/templates/tweet_list.html
twista/templates/tweet_snippet.html
twista/templates/user.html
twista/templates/user_info.html
twista/templates/users_list.html
Twista-0.3.3.dist-info/LICENSE
Twista-0.3.3.dist-info/METADATA
Twista-0.3.3.dist-info/WHEEL
Twista-0.3.3.dist-info/top_level.txt
Twista-0.3.3.dist-info/RECORD
