Metadata-Version: 2.1
Name: Twista
Version: 0.3.3
Summary: Twitter streaming and graph-based analysis framework
Home-page: https://github.com/nkratzke/twista
Author: Nane Kratzke
Author-email: nane.kratzke@th-luebeck.de
License: MIT
Platform: UNKNOWN
Requires-Python: >=3.6,<4.0
Requires-Dist: certifi
Requires-Dist: click (<8.0,>=7.0)
Requires-Dist: tweepy (<4.0,>=3.5)
Requires-Dist: python-dateutil (<3.0,>=2.6)
Requires-Dist: tqdm (<5.0,>=4.35)
Requires-Dist: neo4j (<2.0,>=1.7)
Requires-Dist: termcolor (<1.2,>=1.1)
Requires-Dist: jupyterlab (<2.0,>=1.1)
Requires-Dist: matplotlib (<4.0,>=3.1)
Requires-Dist: py2neo (<5.0,>=4.3)
Requires-Dist: flask (<1.2,>=1.1)
